trashbin.py
qtile_window_trashbin-0.0.2.dist-info/LICENSE
qtile_window_trashbin-0.0.2.dist-info/WHEEL
qtile_window_trashbin-0.0.2.dist-info/METADATA
qtile_window_trashbin-0.0.2.dist-info/RECORD
