Metadata-Version: 2.1
Name: qtile-window-trashbin
Version: 0.0.2
Summary: A thrashbin for qtile windows.
Author-email: Paul Hoffmann <phfn@phfn.de>
Classifier: License :: OSI Approved :: GNU General Public License v3 or later (GPLv3+)
Project-URL: Home, https://phfn.de
Project-URL: Source, https://github.com/phfn/qtile-window-trashbin
